osg/jupyter/__init__.py
osg/jupyter/comanage.py
osg/jupyter/htcondor.py
osg/jupyter/kubespawner.py
osg/jupyter/py.typed
osg_jupyter-1.0.0.dist-info/LICENSE
osg_jupyter-1.0.0.dist-info/WHEEL
osg_jupyter-1.0.0.dist-info/METADATA
osg_jupyter-1.0.0.dist-info/RECORD
