Metadata-Version: 2.1
Name: osg-jupyter
Version: 1.0.0
Summary: Support for OSG for Project Jupyter
Home-page: https://github.com/brianaydemir/osg-jupyter
License: Apache-2.0
Author: Brian Aydemir
Author-email: baydemir@morgridge.org
Requires-Python: >=3.8,<3.9
Classifier: License :: OSI Approved :: Apache Software License
Classifier: Programming Language :: Python :: 3
Classifier: Programming Language :: Python :: 3.8
Requires-Dist: PyJWT (>=1.7,<1.8)
Requires-Dist: PyYAML (>=5.4,<5.5)
Requires-Dist: cryptography (>=3.3.2,<3.4)
Requires-Dist: kubernetes (>=12.0,<12.1)
Requires-Dist: ldap3 (>=2.8,<2.9)
Project-URL: Repository, https://github.com/brianaydemir/osg-jupyter
